cubicweb_intranet/__init__.py
cubicweb_intranet/__pkginfo__.py
cubicweb_intranet/schema.py
cubicweb_intranet/views.py
cubicweb_intranet/i18n/en.po
cubicweb_intranet/i18n/fr.po
cubicweb_intranet/migration/0.11.0_Any.py
cubicweb_intranet/migration/0.13.0_Any.py
cubicweb_intranet/migration/0.13.1_Any.py
cubicweb_intranet/migration/0.13.2_Any.py
cubicweb_intranet/migration/0.13.3_Any.py
cubicweb_intranet/migration/0.13.4_Any.py
cubicweb_intranet/migration/0.15.0_Any.py
cubicweb_intranet/migration/0.16.0_Any.py
cubicweb_intranet/migration/1.2.1_Any.py
cubicweb_intranet/migration/2.1.0_Any.py
cubicweb_intranet/migration/2.11.0_Any.py
cubicweb_intranet/migration/2.2.0_Any.py
cubicweb_intranet/migration/2.3.0_Any.py
cubicweb_intranet/migration/2.4.0_Any.py
cubicweb_intranet/migration/2.5.0_Any.py
cubicweb_intranet/migration/2.6.0_Any.py
cubicweb_intranet-2.14.2.dist-info/METADATA
cubicweb_intranet-2.14.2.dist-info/WHEEL
cubicweb_intranet-2.14.2.dist-info/entry_points.txt
cubicweb_intranet-2.14.2.dist-info/top_level.txt
cubicweb_intranet-2.14.2.dist-info/RECORD
