Metadata-Version: 2.4
Name: cubicweb-intranet
Version: 2.14.2
Summary: an intranet built on the CubicWeb framework
Home-page: http://cubicweb.org/project/cubicweb-intranet
Author: Logilab
Author-email: contact@logilab.fr
License: LGPL
Classifier: Environment :: Web Environment
Classifier: Framework :: CubicWeb
Classifier: Programming Language :: Python
Classifier: Programming Language :: JavaScript
Classifier: Programming Language :: Python :: 3
Classifier: Programming Language :: Python :: 3 :: Only
Requires-Python: >=3.9.2
Requires-Dist: cubicweb[s3]<6.0.0,>=5.0.1
Requires-Dist: cubicweb-api<=0.18.0,>=0.17.1
Requires-Dist: cubicweb-blog<4.0.0,>=3.1.1
Requires-Dist: cubicweb-book<2.0.0,>=1.1.0
Requires-Dist: cubicweb-bootstrap<3.0.0,>=2.1.1
Requires-Dist: cubicweb-card<3.0.0,>=2.1.0
Requires-Dist: cubicweb-comment<4.0.0,>=3.1.0
Requires-Dist: cubicweb-editorjs<0.4.0,>=0.3.0
Requires-Dist: cubicweb-event<3.0.0,>=2.1.0
Requires-Dist: cubicweb-file<5.0.0,>=4.2.0
Requires-Dist: cubicweb-folder<4.0.0,>=3.1.0
Requires-Dist: cubicweb-link<3.0.0,>=2.1.0
Requires-Dist: cubicweb-localperms<2.0.0,>=1.1.0
Requires-Dist: cubicweb-oauth2<2.0.0,>=1.2.1
Requires-Dist: cubicweb-preview<4.0.0,>=3.1.0
Requires-Dist: cubicweb-searchui<2.0.0,>=1.1.0
Requires-Dist: cubicweb-sentry<2.0.0,>=1.1.0
Requires-Dist: cubicweb-signedrequest<4.0.0,>=3.3.1
Requires-Dist: cubicweb-tag<4.0.0,>=3.1.1
Requires-Dist: cubicweb-task<3.0.0,>=2.1.0
Requires-Dist: cubicweb-prometheus<0.7.0,>=0.6.0
Requires-Dist: cubicweb-geocoding<2.0.0,>=1.1.0
Requires-Dist: cubicweb-person<3.0.0,>=2.1.0
Requires-Dist: cubicweb-sioc<2.0.0,>=1.1.0
Requires-Dist: cubicweb-squareui<3.0.0,>=2.1.0
Requires-Dist: cubicweb-web<2.0.0,>=1.6.2
Dynamic: author
Dynamic: author-email
Dynamic: classifier
Dynamic: description
Dynamic: home-page
Dynamic: license
Dynamic: requires-dist
Dynamic: requires-python
Dynamic: summary
